pybotx_smartapp_rpc/__init__.py
pybotx_smartapp_rpc/empty_args.py
pybotx_smartapp_rpc/exception_handlers.py
pybotx_smartapp_rpc/exceptions.py
pybotx_smartapp_rpc/middlewares/__init__.py
pybotx_smartapp_rpc/middlewares/empty_args_middleware.py
pybotx_smartapp_rpc/middlewares/exception_middleware.py
pybotx_smartapp_rpc/models/__init__.py
pybotx_smartapp_rpc/models/errors.py
pybotx_smartapp_rpc/models/method.py
pybotx_smartapp_rpc/models/request.py
pybotx_smartapp_rpc/models/responses.py
pybotx_smartapp_rpc/openapi_utils.py
pybotx_smartapp_rpc/py.typed
pybotx_smartapp_rpc/router.py
pybotx_smartapp_rpc/rpc.py
pybotx_smartapp_rpc/smartapp.py
pybotx_smartapp_rpc/typing.py
pybotx_smartapp_rpc-0.12.0.dist-info/LICENSE
pybotx_smartapp_rpc-0.12.0.dist-info/METADATA
pybotx_smartapp_rpc-0.12.0.dist-info/WHEEL
pybotx_smartapp_rpc-0.12.0.dist-info/RECORD
