Metadata-Version: 2.3
Name: pybotx-smartapp-rpc
Version: 0.12.0
Summary: eXpress SmartApp JSON-RPC library
Author: Arseniy Zhiltsov
Author-email: arseniy.zhiltsov@ccsteam.ru
Requires-Python: >=3.9,<3.14
Classifier: Programming Language :: Python :: 3
Classifier: Programming Language :: Python :: 3.9
Classifier: Programming Language :: Python :: 3.10
Classifier: Programming Language :: Python :: 3.11
Classifier: Programming Language :: Python :: 3.12
Classifier: Programming Language :: Python :: 3.13
Requires-Dist: pybotx (>=0.75.0,<0.76.0)
Requires-Dist: pydantic (>=1.6.0,<1.11.0)
